<?xml version="1.0" encoding="UTF-8"?>
<!DOCTYPE cXML SYSTEM "http://xml.cXML.org/schemas/cXML/1.2.018/Fulfill.dtd">
<cXML payloadID="20150902091737209.cXML_ASNOutbound.314.0@wwt.com" timestamp="2015-09-02T00:00:00-05:00" xml:lang="en">
  <Header>
    <From>
      <Credential domain="NetworkId">
        <Identity>AN01000108350-T</Identity>
      </Credential>
      <Credential domain="VendorSiteID">
        <Identity>3214</Identity>
      </Credential>
      <Credential domain="VendorID">
        <Identity>42613</Identity>
      </Credential>
    </From>
    <To>
      <Credential domain="NetworkId">
        <Identity>AN01009902651-T</Identity>
      </Credential>
    </To>
    <Sender>
      <Credential domain="NetworkId">
        <Identity>AN01000108350-T</Identity>
        <SharedSecret>ariba350</SharedSecret>
      </Credential>
      <UserAgent>WWT WM 1.0</UserAgent>
    </Sender>
  </Header>
  <Request deploymentMode="test">
    <ShipNoticeRequest>
      <ShipNoticeHeader shipmentID="9275510" operation="new" noticeDate="2015-09-02T09:10:25-05:00" shipmentDate="2015-09-02T00:00:00-05:00" deliveryDate="">
        <ServiceLevel xml:lang="Drop Ship - n/a"/>
        <Contact role="shipFrom">
          <Name xml:lang="en"/>
          <PostalAddress>
            <Street>6399 S. Fiddlers Grn Cir Suite 600</Street>
            <Street/>
            <Street/>
            <Street/>
            <City>GREENWOOD VILLAGE</City>
            <State>CO</State>
            <PostalCode>80111</PostalCode>
            <Country isoCountryCode="US">US</Country>
          </PostalAddress>
        </Contact>
        <Contact role="billTo">
          <Name xml:lang="en"/>
          <PostalAddress>
            <Street>APAriba@chartercom.com</Street>
            <Street>PO BOX 31916</Street>
            <Street/>
            <Street/>
            <City>SAINT LOUIS</City>
            <State>MO</State>
            <PostalCode>63131</PostalCode>
            <Country isoCountryCode="US">US</Country>
          </PostalAddress>
        </Contact>
      </ShipNoticeHeader>
      <ShipControl>
        <CarrierIdentifier domain="SCAC">Drop Ship - n/a</CarrierIdentifier>
        <ShipmentIdentifier/>
      </ShipControl>
      <ShipNoticePortion>
        <OrderReference orderID="PO46605" orderDate="2015-09-01T12:00:00-05:00">
          <DocumentReference payloadID=""/>
        </OrderReference>
        <ShipNoticeItem quantity="1" lineNumber="1">
          <UnitOfMeasure>Ea</UnitOfMeasure>
        </ShipNoticeItem>
      </ShipNoticePortion>
    </ShipNoticeRequest>
  </Request>
</cXML>